Workbook

Sheet Read Me
A1: Lawdeck AI Cost Model
A3: Purpose | B3: Estimates what Claude (Anthropic) costs Lawdeck per answer, per student per month, and for the business as a whole, so a price can be set.
A4: How to use | B4: Change only the blue numbers. Yellow cells are the key assumptions to check first. Everything else recalculates.
A5: Sheets | B5: Inputs: all assumptions. Cost per Answer: cost of one message for each task and model. Scenarios: three ways of assigning models to tasks. Monthly Plan: revenue, costs and profit for a chosen scenario.
A6: Key terms | B6: Token: a piece of a word; 1,000 tokens is about 750 words. Input tokens: what Claude reads (instructions, the question, library passages, recent chat). Output tokens: what Claude writes back. One message: one student question plus one Lawdeck reply.
A7: Colour code | B7: Blue text = input you may change. Black = formula. Green = taken from another sheet. Yellow fill = key assumption.
A8: Main caveats | B8: Token sizes and message volumes are estimates until the pilot measures real usage (Lawdeck logs the cost of every call). Exchange rate, hosting prices and payment fees change; update them before relying on totals.
A9: Price source | B9: Claude prices: Anthropic API price list as at October 2026 (Opus 5.5 $4/$20, Sonnet 5.5 $2/$10, Haiku 5.5 $0.10/$0.50 per million input/output tokens; Haiku price applies to prompts up to 100K tokens).
A10: Prepared | B10: 20 October 2026, for internal planning. Not financial advice.

Sheet Inputs
A1: Inputs and assumptions
A3: General
A4: Exchange rate (₦ per US$1) | B4: 1500
A5: Extra output for Claude’s thinking (share of answer length) | B5: 0.3
A6: Target: AI cost as a share of the price | B6: 0.3
A7: Payment processing fee (share of each payment) | B7: 0.015
A9: Claude model prices (US$ per 1 million tokens)
A10: Model | B10: Input (reading) | C10: Output (writing) | D10: Use in Lawdeck
A11: Claude Opus 5.5 | B11: 4 | C11: 20 | D11: Most capable; marking and documents
A12: Claude Sonnet 5.5 | B12: 2 | C12: 10 | D12: Middle; everyday explanations if quality holds
A13: Claude Haiku 5.5 | B13: 0.1 | C13: 0.5 | D13: Cheapest; small jobs, possibly explanations
A15: Task sizes (tokens per message) and monthly volume for a heavy user
A16: Task | B16: Input tokens | C16: Output tokens | D16: Messages per month (heavy user) | E16: What goes in
A17: Everyday explanation | B17: 8000 | C17: 1500 | D17: 150 | E17: Instructions ~1,500 + question ~50 + library passages ~6,000 + recent chat ~500; answer ~1,100 words
A18: Marking a practice answer | B18: 10000 | C18: 2000 | D18: 30 | E18: Instructions, rubric, the student’s answer and library passages; detailed feedback
A19: Producing a document | B19: 6000 | C19: 4000 | D19: 10 | E19: Template, intake answers and instructions; a full document such as a writ or deed
A20: Small jobs (routing, flashcards, titles) | B20: 1000 | C20: 200 | D20: 10 | E20: Short instructions and a short reply
A21: Total messages per month (heavy user) | D21: =SUM(D17:D20) -> 200
A23: Fixed monthly running costs (US$)
A24: Vercel (app hosting) | B24: 20
A25: Supabase (database, sign-in, files) | B25: 25
A26: Voyage AI (library search), monthly allowance | B26: 5
A27: Domain name (about $15 a year) | B27: =15/12 -> 1.25
A28: Total fixed costs per month | B28: =SUM(B24:B27) -> 51.25

Sheet Cost per Answer
A1: Cost of one message (one question and one reply)
A2: Formula: input tokens ÷ 1,000,000 × input price + output tokens × (1 + thinking share) ÷ 1,000,000 × output price
B3: US$ per message | E3: Naira per message
A4: Task | B4: Claude Opus 5.5 | C4: Claude Sonnet 5.5 | D4: Claude Haiku 5.5 | E4: Opus 5.5 (₦) | F4: Sonnet 5.5 (₦) | G4: Haiku 5.5 (₦)
A5: =Inputs!A17 -> Everyday explanation | B5: =Inputs!$B$17/1000000*Inputs!$B$11+Inputs!$C$17*(1+Inputs!$B$5)/1000000*Inputs!$C$11 -> 0.071 | C5: =Inputs!$B$17/1000000*Inputs!$B$12+Inputs!$C$17*(1+Inputs!$B$5)/1000000*Inputs!$C$12 -> 0.0355 | D5: =Inputs!$B$17/1000000*Inputs!$B$13+Inputs!$C$17*(1+Inputs!$B$5)/1000000*Inputs!$C$13 -> 0.001775 | E5: =B5*Inputs!$B$4 -> 106.5 | F5: =C5*Inputs!$B$4 -> 53.25 | G5: =D5*Inputs!$B$4 -> 2.6625
A6: =Inputs!A18 -> Marking a practice answer | B6: =Inputs!$B$18/1000000*Inputs!$B$11+Inputs!$C$18*(1+Inputs!$B$5)/1000000*Inputs!$C$11 -> 0.092 | C6: =Inputs!$B$18/1000000*Inputs!$B$12+Inputs!$C$18*(1+Inputs!$B$5)/1000000*Inputs!$C$12 -> 0.046 | D6: =Inputs!$B$18/1000000*Inputs!$B$13+Inputs!$C$18*(1+Inputs!$B$5)/1000000*Inputs!$C$13 -> 0.0023 | E6: =B6*Inputs!$B$4 -> 138 | F6: =C6*Inputs!$B$4 -> 69 | G6: =D6*Inputs!$B$4 -> 3.45
A7: =Inputs!A19 -> Producing a document | B7: =Inputs!$B$19/1000000*Inputs!$B$11+Inputs!$C$19*(1+Inputs!$B$5)/1000000*Inputs!$C$11 -> 0.128 | C7: =Inputs!$B$19/1000000*Inputs!$B$12+Inputs!$C$19*(1+Inputs!$B$5)/1000000*Inputs!$C$12 -> 0.064 | D7: =Inputs!$B$19/1000000*Inputs!$B$13+Inputs!$C$19*(1+Inputs!$B$5)/1000000*Inputs!$C$13 -> 0.0032 | E7: =B7*Inputs!$B$4 -> 192 | F7: =C7*Inputs!$B$4 -> 96 | G7: =D7*Inputs!$B$4 -> 4.8
A8: =Inputs!A20 -> Small jobs (routing, flashcards, titles) | B8: =Inputs!$B$20/1000000*Inputs!$B$11+Inputs!$C$20*(1+Inputs!$B$5)/1000000*Inputs!$C$11 -> 0.0092 | C8: =Inputs!$B$20/1000000*Inputs!$B$12+Inputs!$C$20*(1+Inputs!$B$5)/1000000*Inputs!$C$12 -> 0.0046 | D8: =Inputs!$B$20/1000000*Inputs!$B$13+Inputs!$C$20*(1+Inputs!$B$5)/1000000*Inputs!$C$13 -> 0.00023 | E8: =B8*Inputs!$B$4 -> 13.8 | F8: =C8*Inputs!$B$4 -> 6.9 | G8: =D8*Inputs!$B$4 -> 0.345

Sheet Scenarios
A1: Three ways to assign Claude models to tasks (one heavy user, per month)
A2: Change the model names in blue to try other combinations. Costs follow automatically.
C3: A. Opus for everything | E3: B. Mixed | G3: C. Lean
A4: Task | B4: Messages per month | C4: Model | D4: Cost (US$) | E4: Model | F4: Cost (US$) | G4: Model | H4: Cost (US$)
A5: =Inputs!A17 -> Everyday explanation | B5: =Inputs!D17 -> 150 | C5: Claude Opus 5.5 | D5: =$B5*INDEX('Cost per Answer'!$B$5:$D$5,MATCH(C5,'Cost per Answer'!$B$4:$D$4,0)) -> 10.65 | E5: Claude Sonnet 5.5 | F5: =$B5*INDEX('Cost per Answer'!$B$5:$D$5,MATCH(E5,'Cost per Answer'!$B$4:$D$4,0)) -> 5.325 | G5: Claude Haiku 5.5 | H5: =$B5*INDEX('Cost per Answer'!$B$5:$D$5,MATCH(G5,'Cost per Answer'!$B$4:$D$4,0)) -> 0.26625
A6: =Inputs!A18 -> Marking a practice answer | B6: =Inputs!D18 -> 30 | C6: Claude Opus 5.5 | D6: =$B6*INDEX('Cost per Answer'!$B$6:$D$6,MATCH(C6,'Cost per Answer'!$B$4:$D$4,0)) -> 2.76 | E6: Claude Opus 5.5 | F6: =$B6*INDEX('Cost per Answer'!$B$6:$D$6,MATCH(E6,'Cost per Answer'!$B$4:$D$4,0)) -> 2.76 | G6: Claude Sonnet 5.5 | H6: =$B6*INDEX('Cost per Answer'!$B$6:$D$6,MATCH(G6,'Cost per Answer'!$B$4:$D$4,0)) -> 1.38
A7: =Inputs!A19 -> Producing a document | B7: =Inputs!D19 -> 10 | C7: Claude Opus 5.5 | D7: =$B7*INDEX('Cost per Answer'!$B$7:$D$7,MATCH(C7,'Cost per Answer'!$B$4:$D$4,0)) -> 1.28 | E7: Claude Opus 5.5 | F7: =$B7*INDEX('Cost per Answer'!$B$7:$D$7,MATCH(E7,'Cost per Answer'!$B$4:$D$4,0)) -> 1.28 | G7: Claude Opus 5.5 | H7: =$B7*INDEX('Cost per Answer'!$B$7:$D$7,MATCH(G7,'Cost per Answer'!$B$4:$D$4,0)) -> 1.28
A8: =Inputs!A20 -> Small jobs (routing, flashcards, titles) | B8: =Inputs!D20 -> 10 | C8: Claude Opus 5.5 | D8: =$B8*INDEX('Cost per Answer'!$B$8:$D$8,MATCH(C8,'Cost per Answer'!$B$4:$D$4,0)) -> 0.092 | E8: Claude Haiku 5.5 | F8: =$B8*INDEX('Cost per Answer'!$B$8:$D$8,MATCH(E8,'Cost per Answer'!$B$4:$D$4,0)) -> 0.0023 | G8: Claude Haiku 5.5 | H8: =$B8*INDEX('Cost per Answer'!$B$8:$D$8,MATCH(G8,'Cost per Answer'!$B$4:$D$4,0)) -> 0.0023
A10: Cost per heavy user per month (US$) | D10: =SUM(D5:D8) -> 14.782 | F10: =SUM(F5:F8) -> 9.3673 | H10: =SUM(H5:H8) -> 2.92855
A11: Cost per heavy user per month (₦) | D11: =D10*Inputs!$B$4 -> 22173 | F11: =F10*Inputs!$B$4 -> 14050.95 | H11: =H10*Inputs!$B$4 -> 4392.825
A12: Average cost per message (US$) | D12: =IF(Inputs!$D$21=0,0,D10/Inputs!$D$21) -> 0.07391 | F12: =IF(Inputs!$D$21=0,0,F10/Inputs!$D$21) -> 0.0468365 | H12: =IF(Inputs!$D$21=0,0,H10/Inputs!$D$21) -> 0.01464275
A13: Price needed for AI to be the target share of price (₦ per month) | D13: =IF(Inputs!$B$6=0,0,D11/Inputs!$B$6) -> 73910 | F13: =IF(Inputs!$B$6=0,0,F11/Inputs!$B$6) -> 46836.5 | H13: =IF(Inputs!$B$6=0,0,H11/Inputs!$B$6) -> 14642.75
A15: Lighter users: cost scales with the number of messages
A16: Messages per month | D16: A (₦) | F16: B (₦) | H16: C (₦)
A17: 20 | D17: =$A17*D$12*Inputs!$B$4 -> 2217.3 | F17: =$A17*F$12*Inputs!$B$4 -> 1405.095 | H17: =$A17*H$12*Inputs!$B$4 -> 439.2825
A18: 60 | D18: =$A18*D$12*Inputs!$B$4 -> 6651.9 | F18: =$A18*F$12*Inputs!$B$4 -> 4215.285 | H18: =$A18*H$12*Inputs!$B$4 -> 1317.8475
A19: 100 | D19: =$A19*D$12*Inputs!$B$4 -> 11086.5 | F19: =$A19*F$12*Inputs!$B$4 -> 7025.475 | H19: =$A19*H$12*Inputs!$B$4 -> 2196.4125
A20: 200 | D20: =$A20*D$12*Inputs!$B$4 -> 22173 | F20: =$A20*F$12*Inputs!$B$4 -> 14050.95 | H20: =$A20*H$12*Inputs!$B$4 -> 4392.825
A21: Assumes lighter users ask the same mix of tasks as the heavy user.

Sheet Monthly Plan
A1: Monthly business picture for one scenario
A3: Your inputs
A4: Scenario to use (A, B or C) | B4: C
A5: Paying students | B5: 500
A6: Average messages per paying student per month | B6: 80
A7: Price per paying student per month (₦) | B7: 5000
A8: Free-tier users | B8: 1000
A9: Messages per free user per month (free-tier limit) | B9: 15
A11: Results (per month)
A12: AI cost per message for the chosen scenario (US$) | B12: =IF(B4="A",Scenarios!D12,IF(B4="B",Scenarios!F12,Scenarios!H12)) -> 0.01464275
A13: Revenue (₦) | B13: =B5*B7 -> 2500000
A14: Payment processing fees (₦) | B14: =B13*Inputs!B7 -> 37500
A15: AI cost: paying students (₦) | B15: =B5*B6*B12*Inputs!B4 -> 878565
A16: AI cost: free-tier users (₦) | B16: =B8*B9*B12*Inputs!B4 -> 329461.88
A17: Fixed running costs (₦) | B17: =Inputs!B28*Inputs!B4 -> 76875
A18: Total costs (₦) | B18: =SUM(B14:B17) -> 1322401.9
A19: Profit or loss (₦) | B19: =B13-B18 -> 1177598.1
A20: Profit margin | B20: =IF(B13=0,0,B19/B13) -> 0.47103925
A21: AI cost as a share of revenue (target in Inputs) | B21: =IF(B13=0,0,(B15+B16)/B13) -> 0.48321075
A22: AI cost per paying student (₦) | B22: =B6*B12*Inputs!B4 -> 1757.13
A23: Paying students needed to break even | B23: =IF((B7*(1-Inputs!B7)-B22)<=0,"Price too low",ROUNDUP((B17+B16)/(B7*(1-Inputs!B7)-B22),0)) -> 129
A25: Free-tier messages are costed at the chosen scenario’s average; limiting free users to the cheapest model would lower this.
